sumologic_mcp/__init__.py
sumologic_mcp/__main__.py
sumologic_mcp/api_client.py
sumologic_mcp/api_discovery.py
sumologic_mcp/api_validator.py
sumologic_mcp/auth.py
sumologic_mcp/config.py
sumologic_mcp/config_validator.py
sumologic_mcp/discovery_logging.py
sumologic_mcp/error_handler.py
sumologic_mcp/main.py
sumologic_mcp/monitoring.py
sumologic_mcp/resilience.py
sumologic_mcp/server.py
sumologic_mcp/time_utils.py
sumologic_mcp/exceptions/__init__.py
sumologic_mcp/models/__init__.py
sumologic_mcp/models/config.py
sumologic_mcp/models/monitor.py
sumologic_mcp/models/responses.py
sumologic_mcp/tools/__init__.py
sumologic_mcp/tools/collector_tools.py
sumologic_mcp/tools/dashboard_tools.py
sumologic_mcp/tools/metrics_tools.py
sumologic_mcp/tools/monitor_error_handler.py
sumologic_mcp/tools/monitor_logging.py
sumologic_mcp/tools/monitor_tools.py
sumologic_mcp/tools/search_tools.py
sumologic_mcp_python-0.1.2.dist-info/METADATA
sumologic_mcp_python-0.1.2.dist-info/WHEEL
sumologic_mcp_python-0.1.2.dist-info/entry_points.txt
sumologic_mcp_python-0.1.2.dist-info/licenses/LICENSE
sumologic_mcp_python-0.1.2.dist-info/RECORD
